{
  "colors": [
    "#cf222e",
    "#953800",
    "#d4a72c",
    "#116329",
    "#0550ae",
    "#8250df",
    "#1f2328",
    "#0969da",
    "#4ac26b",
    "#0a3069",
    "#9a6700",
    "#fd8c73",
    "#f6f8fa",
    "#ffffff",
    "#6639ba",
    "#a40e26",
    "#bf3989",
    "#eaeef2",
    "#ff8182",
    "#bc4c00"
  ],
  "overrides": {
    "astro": {
      "#fe5d01": "#953800"
    },
    "commitlint": {
      "#4fb2dd": "#0550ae"
    },
    "editorconfig": {
      "#6caaaa": "#0550ae"
    },
    "elm": {
      "#5fb4cb": "#0550ae"
    },
    "git": {
      "#e84d32": "#cf222e"
    },
    "html": {
      "#f06529": "#953800"
    },
    "image": {
      "#2dcc9f": "#116329"
    },
    "pnpm": {
      "#4e4e4e": "#1f2328"
    },
    "storybook": {
      "#ff4785": "#bf3989"
    },
    "stylus": {
      "#b3d108": "#116329"
    },
    "vite": {
      "#7293ff": "#8250df"
    },
    "vitest": {
      "#729b1b": "#116329"
    },
    "webpack": {
      "#5599c8": "#0550ae",
      "#75aecb": "#0969da"
    }
  }
}
